esp_helper/__init__.py
esp_helper/firmware.py
esp_helper/main.py
esp_helper/scripts.py
esp_helper/scripts/main.py
esp_helper-0.0.6.dist-info/METADATA
esp_helper-0.0.6.dist-info/WHEEL
esp_helper-0.0.6.dist-info/entry_points.txt
esp_helper-0.0.6.dist-info/top_level.txt
esp_helper-0.0.6.dist-info/RECORD
