Metadata-Version: 2.1
Name: esp-helper
Version: 0.0.6
Summary: An application for streamlining development with ESP chips.
Home-page: https://gitlab.com/jake-barbieur/esp-helper
Author: Jake Barbieur
Author-email: Jake Barbieur <barbieur@gmail.com>
Requires-Python: >=3.7
Requires-Dist: click ==8.1.7
Requires-Dist: requests ==2.32.3
Requires-Dist: beautifulsoup4 ==4.12.3
Requires-Dist: pathlib ==1.0.1
Requires-Dist: urllib3 ==2.2.2
